xgram/__init__.py
xgram/log.py
xgram/telegram.py
xgram/updater.py
xgram-0.1.1.dist-info/DESCRIPTION.rst
xgram-0.1.1.dist-info/METADATA
xgram-0.1.1.dist-info/RECORD
xgram-0.1.1.dist-info/WHEEL
xgram-0.1.1.dist-info/metadata.json
xgram-0.1.1.dist-info/top_level.txt
